[{
    "first_name": "Ker",
    "last_name": "Chidgey",
    "email": "kchidgey0@icio.us",
    "password": "6GQYA!LZ\"~{k"
  }, {
    "first_name": "Kelsey",
    "last_name": "Haliburton",
    "email": "khaliburton1@chron.com",
    "password": "3Vv,(C>YK"
  }, {
    "first_name": "Alejandro",
    "last_name": "Gansbuhler",
    "email": "agansbuhler2@msn.com",
    "password": "37rGQpy`"
  }, {
    "first_name": "Waring",
    "last_name": "Gapper",
    "email": "wgapper3@xinhuanet.com",
    "password": "46M24H#jcIkFIx"
  }, {
    "first_name": "Rosabella",
    "last_name": "Featenby",
    "email": "rfeatenby4@unblog.fr",
    "password": "4yDKKT4CJ!.mx)*"
  }, {
    "first_name": "Hanan",
    "last_name": "Kettel",
    "email": "hkettel5@macromedia.com",
    "password": "4/+(_kMeeh.~x6"
  }, {
    "first_name": "Esta",
    "last_name": "Buttriss",
    "email": "ebuttriss6@bing.com",
    "password": "5~w>SxkxcMUOLUJ8"
  }, {
    "first_name": "Guilbert",
    "last_name": "Largent",
    "email": "glargent7@drupal.org",
    "password": "4~z,HR)F8+nGeOCX"
  }, {
    "first_name": "Antoinette",
    "last_name": "Dellenbrok",
    "email": "adellenbrok8@blogspot.com",
    "password": "1~ZNYcETE@"
  }, {
    "first_name": "Arthur",
    "last_name": "Olechnowicz",
    "email": "aolechnowicz9@examiner.com",
    "password": "2vuw`h}p@lml"
  }, {
    "first_name": "Adan",
    "last_name": "Arundell",
    "email": "aarundella@intel.com",
    "password": "50IHSsY/Jw%q`1C6"
  }, {
    "first_name": "Kelsy",
    "last_name": "Dewett",
    "email": "kdewettb@google.co.jp",
    "password": "6C=Kgk?n6n"
  }, {
    "first_name": "Celka",
    "last_name": "Silvermann",
    "email": "csilvermannc@jalbum.net",
    "password": "3ev&_=mu{MP8o"
  }, {
    "first_name": "Lanni",
    "last_name": "Burkart",
    "email": "lburkartd@redcross.org",
    "password": "3n1q_N&O&+O`2"
  }, {
    "first_name": "Wynn",
    "last_name": "Baltzar",
    "email": "wbaltzare@mashable.com",
    "password": "7{g6F@xqL{j/hX+N"
  }, {
    "first_name": "Tulley",
    "last_name": "Summerlie",
    "email": "tsummerlief@alexa.com",
    "password": "0r#%,.4<"
  }, {
    "first_name": "Gwen",
    "last_name": "Kunzler",
    "email": "gkunzlerg@cbc.ca",
    "password": "7.\\ql)c8h0HUe"
  }, {
    "first_name": "Worden",
    "last_name": "Jorioz",
    "email": "wjoriozh@indiatimes.com",
    "password": "5n3sKk_'Y/g#cRf"
  }, {
    "first_name": "Rolland",
    "last_name": "Yablsley",
    "email": "ryablsleyi@hibu.com",
    "password": "7ZOZUdi#C*E0U"
  }, {
    "first_name": "Oliy",
    "last_name": "Anneslie",
    "email": "oannesliej@example.com",
    "password": "4bC!h8bOT"
  }, {
    "first_name": "Alverta",
    "last_name": "Wolvey",
    "email": "awolveyk@umich.edu",
    "password": "5tZz6\\zyw|*"
  }, {
    "first_name": "Clemens",
    "last_name": "Glasby",
    "email": "cglasbyl@salon.com",
    "password": "6&ifXI7<Nb&TOY"
  }, {
    "first_name": "Ada",
    "last_name": "Dakhno",
    "email": "adakhnom@google.ru",
    "password": "6mzHsDx\""
  }, {
    "first_name": "Shoshanna",
    "last_name": "Buxcy",
    "email": "sbuxcyn@theglobeandmail.com",
    "password": "6poRZso<fK2"
  }, {
    "first_name": "Kalina",
    "last_name": "Guerreru",
    "email": "kguerreruo@pcworld.com",
    "password": "5n2~Y@b*w"
  }, {
    "first_name": "Darill",
    "last_name": "Reames",
    "email": "dreamesp@harvard.edu",
    "password": "0+opExQMO"
  }, {
    "first_name": "Hilarius",
    "last_name": "Swindley",
    "email": "hswindleyq@netscape.com",
    "password": "5?)V=?au9,de"
  }, {
    "first_name": "Pierce",
    "last_name": "Compston",
    "email": "pcompstonr@time.com",
    "password": "8b**#vtq+gWgg/#"
  }, {
    "first_name": "Ulises",
    "last_name": "Jaulmes",
    "email": "ujaulmess@disqus.com",
    "password": "3#KUrwMD}{+C!B"
  }, {
    "first_name": "Murdock",
    "last_name": "Howselee",
    "email": "mhowseleet@altervista.org",
    "password": "9E\\t2iZdsHa|?_"
  }, {
    "first_name": "Karly",
    "last_name": "Jope",
    "email": "kjopeu@fc2.com",
    "password": "6T}@xVJTH)T"
  }, {
    "first_name": "Elana",
    "last_name": "Cancellor",
    "email": "ecancellorv@instagram.com",
    "password": "3%5pzv`hUYUAf`zu"
  }, {
    "first_name": "Verla",
    "last_name": "Bulmer",
    "email": "vbulmerw@eepurl.com",
    "password": "7G$M/z#3fPg"
  }, {
    "first_name": "Bekki",
    "last_name": "Baine",
    "email": "bbainex@theguardian.com",
    "password": "4Q!f?<5Xv"
  }, {
    "first_name": "Cheryl",
    "last_name": "Lemin",
    "email": "cleminy@free.fr",
    "password": "7GF>o>F?6F"
  }, {
    "first_name": "Anabelle",
    "last_name": "Robel",
    "email": "arobelz@hostgator.com",
    "password": "1\\xia75.K.>Xb"
  }, {
    "first_name": "Patricio",
    "last_name": "Quantrill",
    "email": "pquantrill10@furl.net",
    "password": "5TfwrUjLle|"
  }, {
    "first_name": "Arlyne",
    "last_name": "Vondrak",
    "email": "avondrak11@barnesandnoble.com",
    "password": "3KcC8se47%c"
  }, {
    "first_name": "Norton",
    "last_name": "Pennaman",
    "email": "npennaman12@plala.or.jp",
    "password": "4\\1ria6<(%p"
  }, {
    "first_name": "Teri",
    "last_name": "Marten",
    "email": "tmarten13@joomla.org",
    "password": "14@|N#m2wq+*"
  }, {
    "first_name": "Rebbecca",
    "last_name": "Hurlestone",
    "email": "rhurlestone14@jugem.jp",
    "password": "2L!0mgoXyB"
  }, {
    "first_name": "Janaya",
    "last_name": "Raddan",
    "email": "jraddan15@skype.com",
    "password": "8svbx%X,J=c"
  }, {
    "first_name": "Kristopher",
    "last_name": "Brikner",
    "email": "kbrikner16@narod.ru",
    "password": "9<M/!y3AtapwJ0,T"
  }, {
    "first_name": "Wheeler",
    "last_name": "Fust",
    "email": "wfust17@wikia.com",
    "password": "3bsc*LnFdBg<"
  }, {
    "first_name": "Ezri",
    "last_name": "Swetenham",
    "email": "eswetenham18@reddit.com",
    "password": "6lWsU2+&<u*CRcn"
  }, {
    "first_name": "Jeno",
    "last_name": "Alldis",
    "email": "jalldis19@meetup.com",
    "password": "9zvC{,iz`rR"
  }, {
    "first_name": "Sonia",
    "last_name": "Losbie",
    "email": "slosbie1a@apple.com",
    "password": "7NWkf)$P9|dv*eZ\""
  }, {
    "first_name": "Brigg",
    "last_name": "Dunbobin",
    "email": "bdunbobin1b@cocolog-nifty.com",
    "password": "5b&(h~@P!f?)H"
  }, {
    "first_name": "Rafaello",
    "last_name": "Iddy",
    "email": "riddy1c@google.it",
    "password": "2a\"}eLwySG},l>Vb"
  }, {
    "first_name": "Trixy",
    "last_name": "Langhorn",
    "email": "tlanghorn1d@t.co",
    "password": "1dnkxjMjn&5Q"
  }, {
    "first_name": "Shayna",
    "last_name": "Kik",
    "email": "skik1e@latimes.com",
    "password": "5$H?PKGv`RGT"
  }, {
    "first_name": "Roi",
    "last_name": "Kingham",
    "email": "rkingham1f@theglobeandmail.com",
    "password": "5KGq|cuX~jHJnX3m"
  }, {
    "first_name": "Tyrus",
    "last_name": "Grievson",
    "email": "tgrievson1g@com.com",
    "password": "7\"86%8rX{k/do"
  }, {
    "first_name": "Rolfe",
    "last_name": "Stoyell",
    "email": "rstoyell1h@businessweek.com",
    "password": "7vHKc>QMi"
  }, {
    "first_name": "Joye",
    "last_name": "Taillant",
    "email": "jtaillant1i@utexas.edu",
    "password": "4~'rQMvrm9"
  }, {
    "first_name": "Fina",
    "last_name": "Theuss",
    "email": "ftheuss1j@youtu.be",
    "password": "3C3y8qMAuqP08"
  }, {
    "first_name": "Niccolo",
    "last_name": "Rosevear",
    "email": "nrosevear1k@cargocollective.com",
    "password": "1p<\\baaoj"
  }, {
    "first_name": "Demetria",
    "last_name": "Mickleburgh",
    "email": "dmickleburgh1l@yale.edu",
    "password": "1M4iA#6>}"
  }, {
    "first_name": "Jania",
    "last_name": "Matantsev",
    "email": "jmatantsev1m@ft.com",
    "password": "0LMIg~I.9ZHrF"
  }, {
    "first_name": "Ediva",
    "last_name": "Onele",
    "email": "eonele1n@issuu.com",
    "password": "0@(@o)w$.y"
  }, {
    "first_name": "Jesse",
    "last_name": "Lukes",
    "email": "jlukes1o@hc360.com",
    "password": "7ga$uAL\\A\"Z"
  }, {
    "first_name": "Arther",
    "last_name": "Worswick",
    "email": "aworswick1p@w3.org",
    "password": "6Z3A,T5+`"
  }, {
    "first_name": "Nedi",
    "last_name": "Millins",
    "email": "nmillins1q@xing.com",
    "password": "53Lc9Qnp=UD**BhA"
  }, {
    "first_name": "Isidoro",
    "last_name": "Cowpe",
    "email": "icowpe1r@marriott.com",
    "password": "4yy2vIH464<D"
  }, {
    "first_name": "Courtney",
    "last_name": "Cleynman",
    "email": "ccleynman1s@dailymotion.com",
    "password": "2Poc+ij7I&y4"
  }, {
    "first_name": "Murdoch",
    "last_name": "Sedgwick",
    "email": "msedgwick1t@cafepress.com",
    "password": "3?2{tOqf"
  }, {
    "first_name": "Juan",
    "last_name": "Eadmeads",
    "email": "jeadmeads1u@soundcloud.com",
    "password": "7v{yMGKq'e\\mqmm"
  }, {
    "first_name": "Daile",
    "last_name": "Cobello",
    "email": "dcobello1v@google.ru",
    "password": "9qy`Ow`vGk"
  }, {
    "first_name": "Eddie",
    "last_name": "Riping",
    "email": "eriping1w@barnesandnoble.com",
    "password": "9p)4Gc=YN83\"z"
  }, {
    "first_name": "Viki",
    "last_name": "Roelvink",
    "email": "vroelvink1x@unicef.org",
    "password": "5)3L!3qr<${"
  }, {
    "first_name": "Cassius",
    "last_name": "Lerohan",
    "email": "clerohan1y@msn.com",
    "password": "9H?TXhzl"
  }, {
    "first_name": "Dacie",
    "last_name": "Daniel",
    "email": "ddaniel1z@360.cn",
    "password": "8Sgj/N\\cn7r6"
  }, {
    "first_name": "Waylen",
    "last_name": "Chalder",
    "email": "wchalder20@biblegateway.com",
    "password": "2Dwebom~GX|"
  }, {
    "first_name": "Archibald",
    "last_name": "Ojeda",
    "email": "aojeda21@google.co.jp",
    "password": "5xvq83m!I,2<o>k"
  }, {
    "first_name": "Annis",
    "last_name": "Josh",
    "email": "ajosh22@amazon.co.uk",
    "password": "1Q#,#5F$r4"
  }, {
    "first_name": "Faina",
    "last_name": "Zorzi",
    "email": "fzorzi23@qq.com",
    "password": "4Uj>*>dUIKf1#h"
  }, {
    "first_name": "Gui",
    "last_name": "Cotter",
    "email": "gcotter24@vimeo.com",
    "password": "7@~tU3,KfU"
  }, {
    "first_name": "Hanson",
    "last_name": "Bream",
    "email": "hbream25@homestead.com",
    "password": "1WziBF__kRRR"
  }, {
    "first_name": "Zorina",
    "last_name": "Cookney",
    "email": "zcookney26@princeton.edu",
    "password": "8gU&8ETc"
  }, {
    "first_name": "Rolf",
    "last_name": "Jeremaes",
    "email": "rjeremaes27@yelp.com",
    "password": "3T.Cdz/Ldx'j"
  }, {
    "first_name": "Corie",
    "last_name": "Boome",
    "email": "cboome28@canalblog.com",
    "password": "8nlS<NngX,yo"
  }, {
    "first_name": "Valle",
    "last_name": "Farlham",
    "email": "vfarlham29@i2i.jp",
    "password": "9.5{<hq$`a(+ba/+"
  }, {
    "first_name": "Tildie",
    "last_name": "Graver",
    "email": "tgraver2a@who.int",
    "password": "5*+$$U\\Wl(8i"
  }, {
    "first_name": "Myrna",
    "last_name": "Ramelot",
    "email": "mramelot2b@arizona.edu",
    "password": "1r)l43}<c>|0xaBH"
  }, {
    "first_name": "Chrissie",
    "last_name": "Durtnell",
    "email": "cdurtnell2c@tiny.cc",
    "password": "7D(*Qg7CwyS"
  }, {
    "first_name": "Odele",
    "last_name": "Ruoff",
    "email": "oruoff2d@miitbeian.gov.cn",
    "password": "4%02>i\\F"
  }, {
    "first_name": "Cherye",
    "last_name": "Mathivat",
    "email": "cmathivat2e@yolasite.com",
    "password": "0bmC_{*52="
  }, {
    "first_name": "Carolan",
    "last_name": "Dayton",
    "email": "cdayton2f@friendfeed.com",
    "password": "3y3@eTN8fM`Y/L("
  }, {
    "first_name": "Darell",
    "last_name": "Broadfield",
    "email": "dbroadfield2g@uol.com.br",
    "password": "5!E505s3Bci"
  }, {
    "first_name": "Hurley",
    "last_name": "Kewish",
    "email": "hkewish2h@sfgate.com",
    "password": "0!&}plQoF.1/"
  }, {
    "first_name": "Isa",
    "last_name": "MacHostie",
    "email": "imachostie2i@google.com.au",
    "password": "2z4dh!l&M+"
  }, {
    "first_name": "Hatty",
    "last_name": "Coggill",
    "email": "hcoggill2j@msu.edu",
    "password": "9LPMpPK68B!YP~"
  }, {
    "first_name": "Normie",
    "last_name": "Milillo",
    "email": "nmilillo2k@chronoengine.com",
    "password": "6`\\v&GGDV\"\"qsag"
  }, {
    "first_name": "Saw",
    "last_name": "Tooke",
    "email": "stooke2l@topsy.com",
    "password": "1|~8X+zC3.xeL"
  }, {
    "first_name": "Gale",
    "last_name": "Erangy",
    "email": "gerangy2m@mapy.cz",
    "password": "5)u)G_OY"
  }, {
    "first_name": "Berny",
    "last_name": "Vater",
    "email": "bvater2n@google.co.jp",
    "password": "3p=~r>LAj"
  }, {
    "first_name": "Shirlee",
    "last_name": "Otton",
    "email": "sotton2o@sakura.ne.jp",
    "password": "3LKpM9_fL7e=p+"
  }, {
    "first_name": "Wilden",
    "last_name": "Stopher",
    "email": "wstopher2p@wikispaces.com",
    "password": "2L<Ik#`SdK"
  }, {
    "first_name": "Derril",
    "last_name": "Lavell",
    "email": "dlavell2q@webmd.com",
    "password": "1M$f9|oq`Yq&\"V"
  }, {
    "first_name": "Sonya",
    "last_name": "Pettiward",
    "email": "spettiward2r@soundcloud.com",
    "password": "0m*}%},YFC"
  }]